tencentcloud/__init__.py
tencentcloud/wedata/__init__.py
tencentcloud/wedata/v20210820/__init__.py
tencentcloud/wedata/v20210820/errorcodes.py
tencentcloud/wedata/v20210820/models.py
tencentcloud/wedata/v20210820/wedata_client.py
tencentcloud/wedata/v20210820/wedata_client_async.py
tencentcloud/wedata/v20250806/__init__.py
tencentcloud/wedata/v20250806/errorcodes.py
tencentcloud/wedata/v20250806/models.py
tencentcloud/wedata/v20250806/wedata_client.py
tencentcloud/wedata/v20250806/wedata_client_async.py
tencentcloud_sdk_python_wedata-3.1.41.dist-info/METADATA
tencentcloud_sdk_python_wedata-3.1.41.dist-info/WHEEL
tencentcloud_sdk_python_wedata-3.1.41.dist-info/top_level.txt
tencentcloud_sdk_python_wedata-3.1.41.dist-info/RECORD
